tdserver
